{
    "documents": [
        {
            "id": "id__1379",
            "sentiment": "positive",
            "confidenceScores": {
                "positive": 0.96,
                "neutral": 0.02,
                "negative": 0.02
            },
            "sentences": [
                {
                    "sentiment": "neutral",
                    "confidenceScores": {
                        "positive": 0.2,
                        "neutral": 0.8,
                        "negative": 0
                    },
                    "offset": 0,
                    "length": 103,
                    "text": "Adentrar o Hotel Royal é como dar um passo de volta no tempo para uma era de elegância e sofisticação. ",
                    "targets": [
                        {
                            "sentiment": "positive",
                            "confidenceScores": {
                                "positive": 1,
                                "negative": 0
                            },
                            "offset": 11,
                            "length": 11,
                            "text": "Hotel Royal",
                            "relations": [
                                {
                                    "relationType": "assessment",
                                    "ref": "#/documents/0/sentences/0/assessments/0"
                                },
                                {
                                    "relationType": "assessment",
                                    "ref": "#/documents/0/sentences/0/assessments/1"
                                }
                            ]
                        }
                    ],
                    "assessments": [
                        {
                            "sentiment": "positive",
                            "confidenceScores": {
                                "positive": 1,
                                "negative": 0
                            },
                            "offset": 77,
                            "length": 9,
                            "text": "elegância",
                            "isNegated": false
                        },
                        {
                            "sentiment": "positive",
                            "confidenceScores": {
                                "positive": 1,
                                "negative": 0
                            },
                            "offset": 89,
                            "length": 12,
                            "text": "sofisticação",
                            "isNegated": false
                        }
                    ]
                },
                {
                    "sentiment": "positive",
                    "confidenceScores": {
                        "positive": 0.94,
                        "neutral": 0.06,
                        "negative": 0
                    },
                    "offset": 103,
                    "length": 100,
                    "text": "Com sua rica história que remonta aos anos 1950, este hotel exala caráter e charme em cada detalhe. ",
                    "targets": [
                        {
                            "sentiment": "positive",
                            "confidenceScores": {
                                "positive": 1,
                                "negative": 0
                            },
                            "offset": 116,
                            "length": 8,
                            "text": "história",
                            "relations": [
                                {
                                    "relationType": "assessment",
                                    "ref": "#/documents/0/sentences/1/assessments/0"
                                }
                            ]
                        },
                        {
                            "sentiment": "positive",
                            "confidenceScores": {
                                "positive": 1,
                                "negative": 0
                            },
                            "offset": 157,
                            "length": 5,
                            "text": "hotel",
                            "relations": [
                                {
                                    "relationType": "assessment",
                                    "ref": "#/documents/0/sentences/1/assessments/1"
                                },
                                {
                                    "relationType": "assessment",
                                    "ref": "#/documents/0/sentences/1/assessments/2"
                                }
                            ]
                        }
                    ],
                    "assessments": [
                        {
                            "sentiment": "positive",
                            "confidenceScores": {
                                "positive": 1,
                                "negative": 0
                            },
                            "offset": 111,
                            "length": 4,
                            "text": "rica",
                            "isNegated": false
                        },
                        {
                            "sentiment": "positive",
                            "confidenceScores": {
                                "positive": 1,
                                "negative": 0
                            },
                            "offset": 169,
                            "length": 7,
                            "text": "caráter",
                            "isNegated": false
                        },
                        {
                            "sentiment": "positive",
                            "confidenceScores": {
                                "positive": 1,
                                "negative": 0
                            },
                            "offset": 179,
                            "length": 6,
                            "text": "charme",
                            "isNegated": false
                        }
                    ]
                },
                {
                    "sentiment": "positive",
                    "confidenceScores": {
                        "positive": 0.94,
                        "neutral": 0.05,
                        "negative": 0
                    },
                    "offset": 203,
                    "length": 158,
                    "text": "Enquanto alguns podem descrever os móveis do quarto como 'vintage', eu os achei pitorescos e cheios de personalidade, acrescentando ao charme único do lugar.\n",
                    "targets": [
                        {
                            "sentiment": "positive",
                            "confidenceScores": {
                                "positive": 1,
                                "negative": 0
                            },
                            "offset": 238,
                            "length": 6,
                            "text": "móveis",
                            "relations": [
                                {
                                    "relationType": "assessment",
                                    "ref": "#/documents/0/sentences/2/assessments/0"
                                },
                                {
                                    "relationType": "assessment",
                                    "ref": "#/documents/0/sentences/2/assessments/1"
                                }
                            ]
                        },
                        {
                            "sentiment": "positive",
                            "confidenceScores": {
                                "positive": 1,
                                "negative": 0
                            },
                            "offset": 248,
                            "length": 6,
                            "text": "quarto",
                            "relations": [
                                {
                                    "relationType": "assessment",
                                    "ref": "#/documents/0/sentences/2/assessments/0"
                                },
                                {
                                    "relationType": "assessment",
                                    "ref": "#/documents/0/sentences/2/assessments/1"
                                }
                            ]
                        }
                    ],
                    "assessments": [
                        {
                            "sentiment": "positive",
                            "confidenceScores": {
                                "positive": 1,
                                "negative": 0
                            },
                            "offset": 283,
                            "length": 10,
                            "text": "pitorescos",
                            "isNegated": false
                        },
                        {
                            "sentiment": "positive",
                            "confidenceScores": {
                                "positive": 1,
                                "negative": 0
                            },
                            "offset": 306,
                            "length": 13,
                            "text": "personalidade",
                            "isNegated": false
                        }
                    ]
                },
                {
                    "sentiment": "positive",
                    "confidenceScores": {
                        "positive": 1,
                        "neutral": 0,
                        "negative": 0
                    },
                    "offset": 361,
                    "length": 82,
                    "text": "A equipe do Hotel Royal realmente se destaca ao garantir uma estadia encantadora. ",
                    "targets": [
                        {
                            "sentiment": "positive",
                            "confidenceScores": {
                                "positive": 1,
                                "negative": 0
                            },
                            "offset": 374,
                            "length": 11,
                            "text": "Hotel Royal",
                            "relations": [
                                {
                                    "relationType": "assessment",
                                    "ref": "#/documents/0/sentences/3/assessments/0"
                                }
                            ]
                        },
                        {
                            "sentiment": "positive",
                            "confidenceScores": {
                                "positive": 1,
                                "negative": 0
                            },
                            "offset": 423,
                            "length": 7,
                            "text": "estadia",
                            "relations": [
                                {
                                    "relationType": "assessment",
                                    "ref": "#/documents/0/sentences/3/assessments/1"
                                }
                            ]
                        }
                    ],
                    "assessments": [
                        {
                            "sentiment": "positive",
                            "confidenceScores": {
                                "positive": 1,
                                "negative": 0
                            },
                            "offset": 399,
                            "length": 7,
                            "text": "destaca",
                            "isNegated": false
                        },
                        {
                            "sentiment": "positive",
                            "confidenceScores": {
                                "positive": 1,
                                "negative": 0
                            },
                            "offset": 431,
                            "length": 11,
                            "text": "encantadora",
                            "isNegated": false
                        }
                    ]
                },
                {
                    "sentiment": "positive",
                    "confidenceScores": {
                        "positive": 0.9,
                        "neutral": 0,
                        "negative": 0.09
                    },
                    "offset": 443,
                    "length": 192,
                    "text": "Embora tenha havido um pequeno contratempo com a internet durante minha visita, a equipe atenciosa resolveu rapidamente o problema, demonstrando seu compromisso com a satisfação dos hóspedes. ",
                    "targets": [
                        {
                            "sentiment": "negative",
                            "confidenceScores": {
                                "positive": 0.01,
                                "negative": 0.99
                            },
                            "offset": 493,
                            "length": 8,
                            "text": "internet",
                            "relations": [
                                {
                                    "relationType": "assessment",
                                    "ref": "#/documents/0/sentences/4/assessments/0"
                                }
                            ]
                        },
                        {
                            "sentiment": "positive",
                            "confidenceScores": {
                                "positive": 1,
                                "negative": 0
                            },
                            "offset": 526,
                            "length": 6,
                            "text": "equipe",
                            "relations": [
                                {
                                    "relationType": "assessment",
                                    "ref": "#/documents/0/sentences/4/assessments/1"
                                }
                            ]
                        }
                    ],
                    "assessments": [
                        {
                            "sentiment": "negative",
                            "confidenceScores": {
                                "positive": 0.01,
                                "negative": 0.99
                            },
                            "offset": 475,
                            "length": 11,
                            "text": "contratempo",
                            "isNegated": false
                        },
                        {
                            "sentiment": "positive",
                            "confidenceScores": {
                                "positive": 1,
                                "negative": 0
                            },
                            "offset": 533,
                            "length": 9,
                            "text": "atenciosa",
                            "isNegated": false
                        }
                    ]
                },
                {
                    "sentiment": "positive",
                    "confidenceScores": {
                        "positive": 1,
                        "neutral": 0,
                        "negative": 0
                    },
                    "offset": 635,
                    "length": 153,
                    "text": "Além disso, apreciei a conveniência de poder utilizar uma das suas bem equipadas salas de escritório para fazer o check-in do meu voo de volta para casa.",
                    "targets": [
                        {
                            "sentiment": "positive",
                            "confidenceScores": {
                                "positive": 1,
                                "negative": 0
                            },
                            "offset": 717,
                            "length": 5,
                            "text": "salas",
                            "relations": [
                                {
                                    "relationType": "assessment",
                                    "ref": "#/documents/0/sentences/5/assessments/0"
                                },
                                {
                                    "relationType": "assessment",
                                    "ref": "#/documents/0/sentences/5/assessments/1"
                                },
                                {
                                    "relationType": "assessment",
                                    "ref": "#/documents/0/sentences/5/assessments/2"
                                }
                            ]
                        }
                    ],
                    "assessments": [
                        {
                            "sentiment": "positive",
                            "confidenceScores": {
                                "positive": 1,
                                "negative": 0
                            },
                            "offset": 648,
                            "length": 8,
                            "text": "apreciei",
                            "isNegated": false
                        },
                        {
                            "sentiment": "positive",
                            "confidenceScores": {
                                "positive": 1,
                                "negative": 0
                            },
                            "offset": 659,
                            "length": 12,
                            "text": "conveniência",
                            "isNegated": false
                        },
                        {
                            "sentiment": "positive",
                            "confidenceScores": {
                                "positive": 1,
                                "negative": 0
                            },
                            "offset": 703,
                            "length": 13,
                            "text": "bem equipadas",
                            "isNegated": false
                        }
                    ]
                }
            ],
            "warnings": []
        }
    ],
    "errors": [],
    "modelVersion": "2022-11-01"
}